report_of_monaco_2018/__about__.py
report_of_monaco_2018/__init__.py
report_of_monaco_2018/main.py
report_of_monaco_2018/racing.py
report_of_monaco_2018/data_example/__init__.py
report_of_monaco_2018/data_example/abbreviations.txt
report_of_monaco_2018/data_example/end.log
report_of_monaco_2018/data_example/start.log
report_of_monaco_2018-0.0.12.dist-info/METADATA
report_of_monaco_2018-0.0.12.dist-info/WHEEL
report_of_monaco_2018-0.0.12.dist-info/entry_points.txt
report_of_monaco_2018-0.0.12.dist-info/licenses/LICENSE.txt
report_of_monaco_2018-0.0.12.dist-info/RECORD
