Metadata-Version: 2.4
Name: report-of-monaco-2018
Version: 0.0.12
Summary: Monaco 2018 Q1 lap-time report generator
Project-URL: Documentation, https://git.foxminded.ua/YuriiAndrushko/task_6_report_of_monaco_2018
Author-email: Yurii Andrushko <medium12345q@gmail.com>
License-Expression: MIT
License-File: LICENSE.txt
Keywords: F1,Monaco,lap-time,report
Classifier: Programming Language :: Python :: 3.10
Classifier: Programming Language :: Python :: 3.11
Classifier: Programming Language :: Python :: 3.12
Requires-Python: >=3.9
Requires-Dist: argparse
Requires-Dist: pathlib
